cdk_api_mcp_server/__about__.py
cdk_api_mcp_server/__init__.py
cdk_api_mcp_server/models.py
cdk_api_mcp_server/resources.py
cdk_api_mcp_server/server.py
cdk_api_mcp_server/resources/.gitkeep
konokenj_cdk_api_mcp_server-0.2.0.dist-info/METADATA
konokenj_cdk_api_mcp_server-0.2.0.dist-info/WHEEL
konokenj_cdk_api_mcp_server-0.2.0.dist-info/entry_points.txt
konokenj_cdk_api_mcp_server-0.2.0.dist-info/licenses/LICENSE.txt
konokenj_cdk_api_mcp_server-0.2.0.dist-info/RECORD
