Metadata-Version: 2.4
Name: konokenj.cdk-api-mcp-server
Version: 0.2.0
Summary: An MCP server provides AWS CDK API Reference
Project-URL: Documentation, https://github.com/konokenj/cdk-api-mcp-server#readme
Project-URL: Issues, https://github.com/konokenj/cdk-api-mcp-server/issues
Project-URL: Source, https://github.com/konokenj/cdk-api-mcp-server
Author-email: Kenji Kono <konoken@amazon.co.jp>
License-Expression: MIT
License-File: LICENSE.txt
Classifier: Development Status :: 4 - Beta
Classifier: Programming Language :: Python
Classifier: Programming Language :: Python :: 3.8
Classifier: Programming Language :: Python :: 3.9
Classifier: Programming Language :: Python :: 3.10
Classifier: Programming Language :: Python :: 3.11
Classifier: Programming Language :: Python :: 3.12
Classifier: Programming Language :: Python :: Implementation :: CPython
Classifier: Programming Language :: Python :: Implementation :: PyPy
Requires-Python: >=3.8
Requires-Dist: fastmcp>=2.0.0
Requires-Dist: pydantic>=2.10.6
Provides-Extra: dev
Requires-Dist: mypy; extra == 'dev'
Requires-Dist: pygithub; extra == 'dev'
Requires-Dist: semantic-version; extra == 'dev'
